visualpdfdiff/__init__.py
visualpdfdiff/diff.py
visualpdfdiff-1.0.dist-info/LICENSE
visualpdfdiff-1.0.dist-info/METADATA
visualpdfdiff-1.0.dist-info/WHEEL
visualpdfdiff-1.0.dist-info/entry_points.txt
visualpdfdiff-1.0.dist-info/top_level.txt
visualpdfdiff-1.0.dist-info/RECORD
