Metadata-Version: 2.1
Name: visualpdfdiff
Version: 1.0
Summary: Side by side visual comparision differences for PDF documents
Home-page: https://github.com/vokimon/back2back-pdf
Author: David Garcia Garzon
Author-email: voki@canvoki.net
License: GNU General Public License v3 or later (GPLv3+)
Classifier: Programming Language :: Python
Classifier: Programming Language :: Python :: 2
Classifier: Topic :: Software Development :: Libraries :: Python Modules
Classifier: Intended Audience :: Developers
Classifier: Development Status :: 5 - Production/Stable
Classifier: License :: OSI Approved :: GNU General Public License v3 or later (GPLv3+)
Classifier: Operating System :: OS Independent
License-File: LICENSE
Requires-Dist: consolemsg
Requires-Dist: wand
Requires-Dist: PyPdf2
Requires-Dist: future
Requires-Dist: pathlib2 ; python_version < "3.5"
